exiot.py
exiot-0.1.1.dist-info/entry_points.txt
exiot-0.1.1.dist-info/LICENSE
exiot-0.1.1.dist-info/WHEEL
exiot-0.1.1.dist-info/METADATA
exiot-0.1.1.dist-info/RECORD
