Metadata-Version: 2.1
Name: exiot
Version: 0.1.1
Summary: The 'exiot' is a testing tool to test the executable STDIN, STDOUT, STDERR, and many more.
Home-page: https://github.com/pestanko/exiot
License: Apache-2.0
Author: Peter Stanko
Author-email: peter.stanko0@gmail.com
Requires-Python: >=3.8,<4.0
Classifier: License :: OSI Approved :: Apache Software License
Classifier: Programming Language :: Python :: 3
Classifier: Programming Language :: Python :: 3.8
Classifier: Programming Language :: Python :: 3.9
Requires-Dist: PyYAML (>=5.4.1,<6.0.0)
Requires-Dist: junitparser
Project-URL: Documentation, https://github.com/pestanko/exiot
Project-URL: Repository, https://github.com/pestanko/exiot
